libcryptomarket/__init__.py
libcryptomarket/candle/__init__.py
libcryptomarket/candle/exchanges.py
libcryptomarket/candle/inject.py
libcryptomarket/cli/candles.py
libcryptomarket/exchange/__init__.py
libcryptomarket-1.0.0.dist-info/DESCRIPTION.rst
libcryptomarket-1.0.0.dist-info/METADATA
libcryptomarket-1.0.0.dist-info/RECORD
libcryptomarket-1.0.0.dist-info/WHEEL
libcryptomarket-1.0.0.dist-info/entry_points.txt
libcryptomarket-1.0.0.dist-info/metadata.json
libcryptomarket-1.0.0.dist-info/top_level.txt
tests/__init__.py
