Metadata-Version: 2.0
Name: libcryptomarket
Version: 1.0.0
Summary: Library for cryptocurrency market information.
Home-page: https://github.com/gavincyi/libcryptomarket
Author: Gavin Chan
Author-email: gavincyi@gmail.com
License: GNU General Public License v3
Keywords: libcryptomarket
Platform: UNKNOWN
Classifier: Development Status :: 2 - Pre-Alpha
Classifier: Intended Audience :: Developers
Classifier: License :: OSI Approved :: GNU General Public License v3 (GPLv3)
Classifier: Natural Language :: English
Classifier: Programming Language :: Python :: 3
Classifier: Programming Language :: Python :: 3.3
Classifier: Programming Language :: Python :: 3.4
Classifier: Programming Language :: Python :: 3.5
Requires-Dist: ccxt (==1.10.1198)
Requires-Dist: pandas (>=0.20.0)
Requires-Dist: requests[security]
Requires-Dist: setuptools-scm
